[
  {
    "lemma": "fuqborechuo",
    "discriminator": "1",
    "is_official": false,
    "type": "",
    "frame": "",
    "distribution": "",
    "pronominal_class": "",
    "subject": "",
    "sememe": "",
    "examples": [],
    "synonyms": [],
    "etymology": "",
    "etymological_notes": "",
    "langdata": {
      "eng": {
        "id": "Oi7-IzZuP",
        "author": "seaqtaq",
        "date": "2024-10-16T21:44:34.350Z",
        "score": 0
      }
    },
    "definition_type": "informal",
    "eng_definition": "▯ is a clothing iron",
    "eng_notes": "",
    "eng_gloss": ""
  }
]